breadth_first_fragmentation/__init__.py
breadth_first_fragmentation/_modidx.py
breadth_first_fragmentation/fragmentation.py
breadth_first_fragmentation/utilities.py
breadth_first_fragmentation-0.0.2.dist-info/LICENSE
breadth_first_fragmentation-0.0.2.dist-info/METADATA
breadth_first_fragmentation-0.0.2.dist-info/WHEEL
breadth_first_fragmentation-0.0.2.dist-info/entry_points.txt
breadth_first_fragmentation-0.0.2.dist-info/top_level.txt
breadth_first_fragmentation-0.0.2.dist-info/RECORD
