Metadata-Version: 2.1
Name: breadth-first-fragmentation
Version: 0.0.2
Summary: breadth first fragmentation package
Home-page: https://github.com/panukorn17/breadth-first-fragmentation
Author: panukorn17
Author-email: p.taleo17@gmail.com
License: Apache Software License 2.0
Keywords: nbdev jupyter notebook python
Classifier: Development Status :: 4 - Beta
Classifier: Intended Audience :: Developers
Classifier: Natural Language :: English
Classifier: Programming Language :: Python :: 3.7
Classifier: Programming Language :: Python :: 3.8
Classifier: Programming Language :: Python :: 3.9
Classifier: Programming Language :: Python :: 3.10
Classifier: Programming Language :: Python :: 3.11
Classifier: Programming Language :: Python :: 3.12
Classifier: License :: OSI Approved :: Apache Software License
Requires-Python: >=3.7
License-File: LICENSE
Requires-Dist: numpy <2.1,>=1.20
Requires-Dist: pandas <2.3,>=1.2
Requires-Dist: rdkit >=2023.09
Provides-Extra: dev
